aliyunsdkeiam/__init__.py
aliyunsdkeiam/request/__init__.py
aliyunsdkeiam/request/v20211201/AddApplicationAccountToUserRequest.py
aliyunsdkeiam/request/v20211201/AddUserToOrganizationalUnitsRequest.py
aliyunsdkeiam/request/v20211201/AddUsersToGroupRequest.py
aliyunsdkeiam/request/v20211201/AuthorizeApplicationToGroupsRequest.py
aliyunsdkeiam/request/v20211201/AuthorizeApplicationToOrganizationalUnitsRequest.py
aliyunsdkeiam/request/v20211201/AuthorizeApplicationToUsersRequest.py
aliyunsdkeiam/request/v20211201/CreateApplicationClientSecretRequest.py
aliyunsdkeiam/request/v20211201/CreateApplicationFederatedCredentialRequest.py
aliyunsdkeiam/request/v20211201/CreateApplicationRequest.py
aliyunsdkeiam/request/v20211201/CreateApplicationTokenRequest.py
aliyunsdkeiam/request/v20211201/CreateBrandRequest.py
aliyunsdkeiam/request/v20211201/CreateConditionalAccessPolicyRequest.py
aliyunsdkeiam/request/v20211201/CreateDomainProxyTokenRequest.py
aliyunsdkeiam/request/v20211201/CreateDomainRequest.py
aliyunsdkeiam/request/v20211201/CreateFederatedCredentialProviderRequest.py
aliyunsdkeiam/request/v20211201/CreateGroupRequest.py
aliyunsdkeiam/request/v20211201/CreateIdentityProviderRequest.py
aliyunsdkeiam/request/v20211201/CreateInstanceRequest.py
aliyunsdkeiam/request/v20211201/CreateNetworkAccessEndpointRequest.py
aliyunsdkeiam/request/v20211201/CreateNetworkZoneRequest.py
aliyunsdkeiam/request/v20211201/CreateOrganizationalUnitRequest.py
aliyunsdkeiam/request/v20211201/CreateUserRequest.py
aliyunsdkeiam/request/v20211201/DeleteApplicationClientSecretRequest.py
aliyunsdkeiam/request/v20211201/DeleteApplicationFederatedCredentialRequest.py
aliyunsdkeiam/request/v20211201/DeleteApplicationRequest.py
aliyunsdkeiam/request/v20211201/DeleteApplicationTokenRequest.py
aliyunsdkeiam/request/v20211201/DeleteBrandRequest.py
aliyunsdkeiam/request/v20211201/DeleteConditionalAccessPolicyRequest.py
aliyunsdkeiam/request/v20211201/DeleteDomainProxyTokenRequest.py
aliyun_python_sdk_eiam-1.0.4.dist-info/LICENSE
aliyun_python_sdk_eiam-1.0.4.dist-info/METADATA
aliyun_python_sdk_eiam-1.0.4.dist-info/WHEEL
aliyun_python_sdk_eiam-1.0.4.dist-info/top_level.txt
aliyun_python_sdk_eiam-1.0.4.dist-info/RECORD
